{"cameraMode":{"drawMode":0,"name":"Shaded","section":"Shading Mode"},"sceneLighting":true,"audioPlay":false,"sceneViewState":{"m_AlwaysRefresh":false,"showFog":true,"showSkybox":true,"showFlares":true,"showImageEffects":true,"showParticleSystems":true,"showVisualEffectGraphs":true,"m_FxEnabled":true},"in2DMode":false,"pivot":{"x":5.280653953552246,"y":13.679160118103028,"z":-10.710667610168457},"rotation":{"x":0.3164568543434143,"y":-0.5258949995040894,"z":0.21963857114315034,"w":0.7584372758865356},"size":2.844743251800537,"orthographic":false}